gp/__init__.py
gp/actors/data/__init__.py
gp/actors/data/_data.py
gp/actors/data/_db.py
gp/actors/el/__init__.py
gp/actors/el/cangen.py
gp/actors/el/canrank.py
gp/actors/el/canreg.py
gp/actors/el/prelude.py
gp/actors/sm/__init__.py
gp/actors/sm/can_graph.py
gp/actors/sm/graph_inference.py
gp/actors/sm/prelude.py
gp/distantsupervision/README.md
gp/distantsupervision/__init__.py
gp/distantsupervision/datasets/__init__.py
gp/distantsupervision/datasets/make_autolabel.py
gp/distantsupervision/datasets/make_dataset_helper.py
gp/distantsupervision/datasets/s01_make_dataset_v1.ipynb
gp/distantsupervision/datasets/s01_make_dataset_v2.ipynb
gp/distantsupervision/datasets/s02_make_autolabel.ipynb
gp/distantsupervision/datasets/taxonomy_helper.py
gp/distantsupervision/make_dataset/__init__.py
gp/distantsupervision/make_dataset/erv1.py
gp/distantsupervision/make_dataset/fbhct.py
gp/distantsupervision/make_dataset/fbt.py
gp/distantsupervision/make_dataset/fcom.py
gp/distantsupervision/make_dataset/fentcol.py
gp/distantsupervision/make_dataset/freg.py
gp/distantsupervision/make_dataset/fv1.py
gp/distantsupervision/make_dataset/interface.py
gp/distantsupervision/make_dataset/lv1.py
gp/distantsupervision/make_dataset/lv2.py
gp/distantsupervision/make_dataset/mv1.py
gp/distantsupervision/make_dataset/mv2.py
gp/distantsupervision/make_dataset/prelude.py
gp/distantsupervision/make_dataset/utils.py
gp/entity_linking/__init__.py
gp/entity_linking/candidate_generation/__init__.py
gp/entity_linking/candidate_generation/common.py
gp/entity_linking/candidate_generation/fuzzy_search.py
gp/entity_linking/candidate_generation/localsearch.py
gp/entity_linking/candidate_generation/oracle_model.py
gp/entity_linking/candidate_ranking/__init__.py
gp/entity_linking/candidate_ranking/common.py
gp/entity_linking/candidate_ranking/feats/__init__.py
gp/entity_linking/candidate_ranking/feats/feat_fn.py
gp/entity_linking/candidate_ranking/feats/get_candidates.py
gramsplus_2-6.0.2.dist-info/LICENSE
gramsplus_2-6.0.2.dist-info/METADATA
gramsplus_2-6.0.2.dist-info/WHEEL
gramsplus_2-6.0.2.dist-info/entry_points.txt
gramsplus_2-6.0.2.dist-info/RECORD
